cli.py
add/__init__.py
add/utils.py
add/ddd/domain/__name__/__init__.py.jinja2
add/ddd/domain/__name__/entities.py.jinja2
add/ddd/domain/__name__/repository.py.jinja2
add/ddd/infrastructure/sqlalchemy/__name___table.py.jinja2
add/ddd/infrastructure/sqlalchemy/repository/__name__.py.jinja2
add/ddd/infrastructure/tortoise/__name___table.py.jinja2
add/ddd/infrastructure/tortoise/repository/__name__.py.jinja2
add/ddd/operational/__name__.py.jinja2
add/ddd/presentation/__name__/__init__.py.jinja2
add/ddd/presentation/__name__/contracts.py.jinja2
add/ddd/presentation/__name__/rest.py.jinja2
add/mvc/models/sqlalchemy/repository.py.jinja2
add/mvc/models/sqlalchemy/table.py.jinja2
add/mvc/models/tortoise/repository.py.jinja2
add/mvc/models/tortoise/table.py.jinja2
add/mvc/views/__name__.py.jinja2
create/__init__.py
create/utils.py
create/common/.dockerignore
create/common/.env.example
create/common/.gitignore
create/common/Makefile.jinja2
create/common/README.md.jinja2
create/common/alembic.ini.jinja2
create/common/docker-compose.yml
create/common/pyproject.toml.jinja2
create/common/compose/app/Dockerfile.jinja2
create/common/compose/app/dev.sqlalchemy.sh
create/common/compose/app/dev.tortoise.sh
create/common/compose/app/prod.sqlalchemy.py
create/common/compose/app/prod.tortoise.py
create/ddd/__init__.py
create/ddd/server.py
create/ddd/config/__init__.py
create/ddd/config/authentication.py
create/ddd/config/cache.py
create/ddd/config/core.py
create/ddd/config/cors.py
create/ddd/config/database.py
create/ddd/config/logging.py
create/ddd/config/mailing.py
create/ddd/config/public_api.py
create/ddd/config/integrations/__init__.py
create/ddd/config/integrations/frontend.py
create/ddd/domain/__init__.py
create/ddd/domain/authentication/__init__.py
create/ddd/domain/authentication/validators.py
create/ddd/domain/users/__init__.py
create/ddd/domain/users/constants.py
create/ddd/domain/users/entities.py
create/ddd/domain/users/repository.py
create/ddd/domain/users/services.py
robyn_config-0.3.1.dist-info/licenses/LICENSE
robyn_config-0.3.1.dist-info/METADATA
robyn_config-0.3.1.dist-info/WHEEL
robyn_config-0.3.1.dist-info/entry_points.txt
robyn_config-0.3.1.dist-info/top_level.txt
robyn_config-0.3.1.dist-info/RECORD
