Metadata-Version: 2.4
Name: robyn-config
Version: 0.3.1
Summary: A powerful CLI tool to bootstrap and manage production-ready Robyn applications with best practices built-in.
Author-email: Leshqa <slav4ik77777@gmail.com>
License: MIT
Requires-Python: <4.0,>=3.11
License-File: LICENSE
Requires-Dist: click>=8.1.7
Requires-Dist: Jinja2>=3.1
Provides-Extra: dev
Requires-Dist: ruff>=0.6.0; extra == "dev"
Requires-Dist: black>=24.10.0; extra == "dev"
Requires-Dist: pytest>=7.4.0; extra == "dev"
Requires-Dist: httpx>=0.27.0; extra == "dev"
Requires-Dist: build>=1.2.1; extra == "dev"
Requires-Dist: twine>=1.6.0; extra == "dev"
Requires-Dist: Sphinx>=8.0.0; extra == "dev"
Requires-Dist: sphinx-rtd-theme>=3.0.0; extra == "dev"
Requires-Dist: myst-parser>=2.0.0; extra == "dev"
Dynamic: license-file
